cenc/__init__.py
cenc/main.py
cenc-0.2.0.dist-info/entry_points.txt
cenc-0.2.0.dist-info/WHEEL
cenc-0.2.0.dist-info/METADATA
cenc-0.2.0.dist-info/RECORD
